example_agent_sithumi
