Metadata-Version: 2.1
Name: example-agent-sithumi
Version: 1.3
Summary: This will return Sithumi's info.
Requires-Dist: pandas
Requires-Dist: numpy
